Metadata-Version: 2.1
Name: elasticflow
Version: 0.0.1
Summary: An elastic, distributed python compute platform
Home-page: UNKNOWN
Author: Darren Govoni
Author-email: darren@ontrenet.com
License: MIT
Keywords: parallel processing,devops,dataflow,supercomputing,workflows
Platform: UNKNOWN
Classifier: Development Status :: 2 - Pre-Alpha
Classifier: Intended Audience :: Developers
Classifier: Programming Language :: Python :: 3.9
Requires-Python: >=3.8.*
